processamento_de_imagens_marcelo/__init__.py
processamento_de_imagens_marcelo/processing/__init__.py
processamento_de_imagens_marcelo/processing/combination.py
processamento_de_imagens_marcelo/processing/transformation.py
processamento_de_imagens_marcelo/utils/__init__.py
processamento_de_imagens_marcelo/utils/io.py
processamento_de_imagens_marcelo/utils/plot.py
image_processing_M_teste-0.0.2.dist-info/METADATA
image_processing_M_teste-0.0.2.dist-info/WHEEL
image_processing_M_teste-0.0.2.dist-info/top_level.txt
image_processing_M_teste-0.0.2.dist-info/RECORD
