Metadata-Version: 2.1
Name: image-processing-M-teste
Version: 0.0.2
Summary: Processamento de imagem. This project belongs to Karina Tiemi Kato, Tech Lead, Machine Learning Engineer, Data Scientist Specialist at Take. This package is a demo for simulation of upload on the Test Pypi website, and it's from class of the Bootcamp developer full stack Python. E-mail:karinatkato@gmail.com
Home-page: https://github.com/Marcelo-Mandler
Author: Marcelo Mandler
Author-email: marcelod2mandler@yahoo.com.br
License: UNKNOWN
Platform: UNKNOWN
Requires-Python: >=3.8
Requires-Dist: pip
Requires-Dist: setuptools
